LICENSE
MANIFEST.in
README.rst
requirements.txt
setup.py
dwolla/__init__.py
dwolla.egg-info/PKG-INFO
dwolla.egg-info/SOURCES.txt
dwolla.egg-info/dependency_links.txt
dwolla.egg-info/requires.txt
dwolla.egg-info/top_level.txt