Metadata-Version: 1.0
Name: dwolla
Version: 1.6.2
Summary: Dwolla Client API
Home-page: https://github.com/dwolla/dwolla-python
Author: Michael Schonfeld
Author-email: michael@dwolla.com
License: MIT
Platform: UNKNOWN
Classifier: Development Status :: 4 - Beta
Classifier: Intended Audience :: Developers
Classifier: License :: OSI Approved :: MIT License
Classifier: Operating System :: OS Independent
Classifier: Programming Language :: Python :: 2.6
Classifier: Programming Language :: Python :: 2.7
Classifier: Topic :: Office/Business :: Financial :: Point-Of-Sale
Classifier: Topic :: Software Development :: Libraries :: Python Modules
